squid/__init__.py
squid_qml-21.3.1.dist-info/METADATA
squid_qml-21.3.1.dist-info/WHEEL
squid_qml-21.3.1.dist-info/top_level.txt
squid_qml-21.3.1.dist-info/RECORD
