Metadata-Version: 2.1
Name: squid-qml
Version: 21.3.1
Summary: SQUID: Hybrid Quantum-Classical ML package
Home-page: https://bitbucket.org/squid-qml/squid
Author: Jakub Filipek
License: UNKNOWN
Platform: UNKNOWN
Requires-Dist: numpy (>=1.19.1)
Requires-Dist: pyyaml (>=5.3.1)
Requires-Dist: torch (>=1.6.0)
Requires-Dist: torchvision (>=0.7.0)
